{
  "$schema": "https://ui.shadcn.com/schema/registry.json",
  "name": "domino",
  "homepage": "https://domino-registry.vercel.app",
  "items": [
    {
      "name": "button",
      "type": "registry:component",
      "title": "Button",
      "description": "Button primitive",
      "files": [
        {
          "path": "registry/domino/ui/button.tsx",
          "type": "registry:component"
        }
      ]
    },
    {
      "name": "input",
      "type": "registry:component",
      "title": "Input",
      "description": "Input primitive",
      "files": [
        {
          "path": "registry/domino/ui/input.tsx",
          "type": "registry:component"
        }
      ]
    },
    {
      "name": "label",
      "type": "registry:component",
      "title": "Label",
      "description": "Label primitive",
      "files": [
        {
          "path": "registry/domino/ui/label.tsx",
          "type": "registry:component"
        }
      ]
    },
    {
      "name": "textarea",
      "type": "registry:component",
      "title": "Textarea",
      "description": "Textarea primitive",
      "files": [
        {
          "path": "registry/domino/ui/textarea.tsx",
          "type": "registry:component"
        }
      ]
    },
    {
      "name": "card",
      "type": "registry:component",
      "title": "Card",
      "description": "Card primitive",
      "files": [
        {
          "path": "registry/domino/ui/card.tsx",
          "type": "registry:component"
        }
      ]
    },
    {
      "name": "hello-world",
      "type": "registry:component",
      "title": "Hello World",
      "description": "A simple hello world component",
      "registryDependencies": [
        "button"
      ],
      "files": [
        {
          "path": "registry/domino/blocks/hello-world/hello-world.tsx",
          "type": "registry:component"
        }
      ]
    },
    {
      "name": "example-form",
      "type": "registry:component",
      "title": "Example Form",
      "description": "A contact form with Zod validation.",
      "dependencies": [
        "zod"
      ],
      "registryDependencies": [
        "button",
        "input",
        "label",
        "textarea",
        "card"
      ],
      "files": [
        {
          "path": "registry/domino/blocks/example-form/example-form.tsx",
          "type": "registry:component"
        }
      ]
    },
    {
      "name": "complex-component",
      "type": "registry:component",
      "title": "Complex Component",
      "description": "A complex component showing hooks, libs and components.",
      "registryDependencies": [
        "card"
      ],
      "files": [
        {
          "path": "registry/domino/blocks/complex-component/page.tsx",
          "type": "registry:page",
          "target": "app/pokemon/page.tsx"
        },
        {
          "path": "registry/domino/blocks/complex-component/components/pokemon-card.tsx",
          "type": "registry:component"
        },
        {
          "path": "registry/domino/blocks/complex-component/components/pokemon-image.tsx",
          "type": "registry:component"
        },
        {
          "path": "registry/domino/blocks/complex-component/lib/pokemon.ts",
          "type": "registry:lib"
        },
        {
          "path": "registry/domino/blocks/complex-component/hooks/use-pokemon.ts",
          "type": "registry:hook"
        }
      ]
    },
    {
      "name": "example-with-css",
      "type": "registry:component",
      "title": "Example with CSS",
      "description": "A login form with a CSS file.",
      "files": [
        {
          "path": "registry/domino/blocks/example-with-css/example-card.tsx",
          "type": "registry:component"
        },
        {
          "path": "registry/domino/blocks/example-with-css/example-card.css",
          "type": "registry:component"
        }
      ]
    },
    {
      "name": "login-form",
      "type": "registry:block",
      "title": "Login Form",
      "description": "A login form",
      "registryDependencies": [
        "button",
        "input",
        "label",
        "card"
      ],
      "files": [
        {
          "path": "registry/domino/blocks/login-form/login-form.tsx",
          "type": "registry:block"
        }
      ]
    }
  ]
}